MANIFEST.in
README.txt
setup.py
foolib/__init__.py
foolib/bar.py
foolib/foo.py
foolib.egg-info/PKG-INFO
foolib.egg-info/SOURCES.txt
foolib.egg-info/dependency_links.txt
foolib.egg-info/top_level.txt