Metadata-Version: 1.0
Name: foolib
Version: 0.0.1
Summary: Does something foo
Home-page: https://www.retailreco.com/foolib
Author: Vivek
Author-email: tiwarivivek2217@gmail.com
License: UNKNOWN
Platform: UNKNOWN
Classifier: Programming Language :: Python
Classifier: Programming Language :: Python :: 2
Classifier: License :: OSI Approved :: GNU General Public License (GPL)
Classifier: Operating System :: OS Independent
Classifier: Development Status :: 1 - Planning
Classifier: Environment :: Console
Classifier: Intended Audience :: Science/Research
Classifier: Topic :: Scientific/Engineering :: GIS
